django_ansi2html_filter
django_ansi2html_filter/templatetags
