Metadata-Version: 1.0
Name: django-ansi2html-filter
Version: 0.0.2
Summary: Apply ansi2html transformation in Django templates
Home-page: http://www.dabapps.com
Author: DabApps
Author-email: contact@dabapps.com
License: GPL
Platform: UNKNOWN
